lingvue/__init__.py
tests/__init__.py
lingvue-0.0.1.dist-info/METADATA
lingvue-0.0.1.dist-info/WHEEL
lingvue-0.0.1.dist-info/licenses/LICENSE
lingvue-0.0.1.dist-info/RECORD
